[
  {
    "line": 1,
    "elements": [
      {
        "line": 36,
        "name": "Check in MainPage add multiple products",
        "description": "",
        "id": "test-saucedemo-website---wizeline-qa-automation-bootcamp;check-in-mainpage-add-multiple-products",
        "type": "scenario",
        "keyword": "Scenario",
        "steps": [
          {
            "result": {
              "duration": 5860177400,
              "status": "passed"
            },
            "line": 38,
            "name": "user is on LOGIN page Scenario",
            "match": {
              "location": "TC1_LoginStep.user_is_on_LOGIN_page_Scenario()"
            },
            "keyword": "Given "
          },
          {
            "result": {
              "duration": 4437414600,
              "status": "passed"
            },
            "line": 39,
            "name": "user enter userName and password",
            "match": {
              "location": "TC1_LoginStep.user_enter_userName_and_password()"
            },
            "keyword": "When "
          },
          {
            "result": {
              "duration": 198391800,
              "status": "passed"
            },
            "line": 40,
            "name": "clicks on LOGIN button",
            "match": {
              "location": "TC1_LoginStep.clicks_on_LOGIN_button()"
            },
            "keyword": "And "
          },
          {
            "result": {
              "duration": 8757513100,
              "status": "passed"
            },
            "line": 41,
            "name": "user add multiple products",
            "match": {
              "location": "TC5_AddMultipleProducts.user_add_multiple_products()"
            },
            "keyword": "Then "
          },
          {
            "result": {
              "duration": 2797790000,
              "status": "passed"
            },
            "line": 42,
            "name": "basket products are checked",
            "match": {
              "location": "TC5_AddMultipleProducts.basket_products_are_checked()"
            },
            "keyword": "And "
          }
        ],
        "tags": [
          {
            "line": 35,
            "name": "@addMultipleProducts"
          }
        ]
      }
    ],
    "name": "Test sauceDemo WebSite - WizeLine QA Automation BootCamp",
    "description": "",
    "id": "test-saucedemo-website---wizeline-qa-automation-bootcamp",
    "keyword": "Feature",
    "uri": "scenariosGherkin.feature"
  }
]